py_ai_trust/__init__.py
py_ai_trust/auditor.py
py_ai_trust/explainability.py
py_ai_trust/fairness.py
py_ai_trust/mitigation.py
py_ai_trust/privacy.py
py_ai_trust/robustness.py
py_ai_trust/utils.py
py_ai_trust-0.1.0.dist-info/licenses/LICENSE
py_ai_trust-0.1.0.dist-info/METADATA
py_ai_trust-0.1.0.dist-info/WHEEL
py_ai_trust-0.1.0.dist-info/top_level.txt
py_ai_trust-0.1.0.dist-info/RECORD
