Metadata-Version: 2.4
Name: py-ai-trust
Version: 0.1.0
Summary: A comprehensive Python library for building trustworthy and responsible AI systems, focusing on fairness, robustness, privacy, and explainability.
Author-email: 3rror_py <your.email@example.com>
Project-URL: Homepage, https://github.com/your-username/py-ai-trust
Project-URL: Bug Tracker, https://github.com/your-username/py-ai-trust/issues
Keywords: ai-ethics,responsible-ai,fairness,bias-detection,bias-mitigation,explainable-ai,xai,model-interpretability,robustness,adversarial-attacks,ai-privacy,trustworthy-ai,mlops,audit,compliance
Classifier: Programming Language :: Python :: 3
Classifier: License :: OSI Approved :: MIT License
Classifier: Operating System :: OS Independent
Classifier: Development Status :: 3 - Alpha
Classifier: Intended Audience :: Developers
Classifier: Intended Audience :: Science/Research
Classifier: Topic :: Scientific/Engineering :: Artificial Intelligence
Classifier: Topic :: Software Development :: Libraries :: Python Modules
Classifier: Topic :: Security
Classifier: Topic :: Scientific/Engineering :: Information Analysis
Requires-Python: >=3.8
License-File: LICENSE
Requires-Dist: numpy>=1.20.0
Requires-Dist: pandas>=1.0.0
Requires-Dist: scikit-learn>=1.0.0
Requires-Dist: matplotlib>=3.0.0
Requires-Dist: seaborn>=0.11.0
Requires-Dist: scipy>=1.5.0
Requires-Dist: tqdm>=4.0.0
Provides-Extra: adversarial
Requires-Dist: adversarial-robustness-toolbox[pytorch]>=1.0.0; extra == "adversarial"
Provides-Extra: privacy
Requires-Dist: opacus>=1.0.0; extra == "privacy"
Dynamic: license-file
